[{"name":"ALIBABA GROUP HLDG LTD","class":"SPONSORED ADS","cusip":"01609W102","value":"58,673","shares":"258,721","shPrn":"SH","putCall":" ","investmentDiscretion":"SOLE","otherManager":" ","sole":"258,721","shared":"0","none":"0"},{"name":"MICRON TECHNOLOGY INC","class":"COM","cusip":"595112103","value":"131,889","shares":"1,552,000","shPrn":"SH","putCall":" ","investmentDiscretion":"SOLE","otherManager":" ","sole":"1,552,000","shared":"0","none":"0"},{"name":"SERITAGE GROWTH PPTYS","class":"CL A","cusip":"81752R100","value":"87,089","shares":"4,733,118","shPrn":"SH","putCall":" ","investmentDiscretion":"SOLE","otherManager":" ","sole":"4,188,609","shared":"0","none":"544,509"}]