[{
    "investor": "Pat Dorsey",
    "fund": "Dorsey Asset Management, LLC",
    "CIK": "0001671657",
    "period_of_report":"Q3-21",
    "holdings":
    [
    {
        "name": "ALPHABET INC",
        "class": "CAP STK CL C",
        "cusip": "02079K107",
        "value": "66,390",
        "shares": "24,909",
        "shPrn": "SH",
        "putCall": " ",
        "investmentDiscretion": "SOLE",
        "otherManager": " ",
        "sole": "24,909",
        "shared": "0",
        "none": "0"
    },
    {
        "name": "DISNEY WALT CO",
        "class": "COM",
        "cusip": "254687106",
        "value": "131,572",
        "shares": "777,753",
        "shPrn": "SH",
        "putCall": " ",
        "investmentDiscretion": "SOLE",
        "otherManager": " ",
        "sole": "777,753",
        "shared": "0",
        "none": "0"
    },
    {
        "name": "EBAY INC.",
        "class": "COM",
        "cusip": "278642103",
        "value": "115,543",
        "shares": "1,658,432",
        "shPrn": "SH",
        "putCall": " ",
        "investmentDiscretion": "SOLE",
        "otherManager": " ",
        "sole": "1,658,432",
        "shared": "0",
        "none": "0"
    },
    {
        "name": "FACEBOOK INC",
        "class": "CL A",
        "cusip": "30303M102",
        "value": "195,316",
        "shares": "575,491",
        "shPrn": "SH",
        "putCall": " ",
        "investmentDiscretion": "SOLE",
        "otherManager": " ",
        "sole": "575,491",
        "shared": "0",
        "none": "0"
    },
    {
        "name": "PAYPAL HLDGS INC",
        "class": "COM",
        "cusip": "70450Y103",
        "value": "147,993",
        "shares": "568,745",
        "shPrn": "SH",
        "putCall": " ",
        "investmentDiscretion": "SOLE",
        "otherManager": " ",
        "sole": "568,745",
        "shared": "0",
        "none": "0"
    },
    {
        "name": "SEMRUSH HLDGS INC",
        "class": "CL A COM",
        "cusip": "81686C104",
        "value": "58,820",
        "shares": "2,550,725",
        "shPrn": "SH",
        "putCall": " ",
        "investmentDiscretion": "SOLE",
        "otherManager": " ",
        "sole": "2,550,725",
        "shared": "0",
        "none": "0"
    },
    {
        "name": "SMARTSHEET INC",
        "class": "COM CL A",
        "cusip": "83200N103",
        "value": "190,899",
        "shares": "2,773,894",
        "shPrn": "SH",
        "putCall": " ",
        "investmentDiscretion": "SOLE",
        "otherManager": " ",
        "sole": "2,773,894",
        "shared": "0",
        "none": "0"
    },
    {
        "name": "UPWORK INC",
        "class": "COM",
        "cusip": "91688F104",
        "value": "72,947",
        "shares": "1,619,966",
        "shPrn": "SH",
        "putCall": " ",
        "investmentDiscretion": "SOLE",
        "otherManager": " ",
        "sole": "1,619,966",
        "shared": "0",
        "none": "0"
    },
    {
        "name": "WIX COM LTD",
        "class": "SHS",
        "cusip": "M98068105",
        "value": "166,153",
        "shares": "847,847",
        "shPrn": "SH",
        "putCall": " ",
        "investmentDiscretion": "SOLE",
        "otherManager": " ",
        "sole": "847,847",
        "shared": "0",
        "none": "0"
    }
]}]