[{"name":"ALPHABET INC","class":"CAP STK CL C","cusip":"02079K107","value":"61,949","shares":"24,717","shPrn":"SH","putCall":" ","investmentDiscretion":"SOLE","otherManager":" ","sole":"24,717","shared":"0","none":"0"},{"name":"DESPEGAR COM CORP","class":"ORD SHS","cusip":"G27358103","value":"43,862","shares":"3,320,397","shPrn":"SH","putCall":" ","investmentDiscretion":"SOLE","otherManager":" ","sole":"3,320,397","shared":"0","none":"0"},{"name":"DISNEY WALT CO","class":"COM","cusip":"254687106","value":"124,721","shares":"709,571","shPrn":"SH","putCall":" ","investmentDiscretion":"SOLE","otherManager":" ","sole":"709,571","shared":"0","none":"0"},{"name":"EBAY INC.","class":"COM","cusip":"278642103","value":"160,323","shares":"2,283,476","shPrn":"SH","putCall":" ","investmentDiscretion":"SOLE","otherManager":" ","sole":"2,283,476","shared":"0","none":"0"},{"name":"FACEBOOK INC","class":"CL A","cusip":"30303M102","value":"235,238","shares":"676,536","shPrn":"SH","putCall":" ","investmentDiscretion":"SOLE","otherManager":" ","sole":"676,536","shared":"0","none":"0"},{"name":"PAYPAL HLDGS INC","class":"COM","cusip":"70450Y103","value":"159,988","shares":"548,880","shPrn":"SH","putCall":" ","investmentDiscretion":"SOLE","otherManager":" ","sole":"548,880","shared":"0","none":"0"},{"name":"SMARTSHEET INC","class":"COM CL A","cusip":"83200N103","value":"231,583","shares":"3,202,198","shPrn":"SH","putCall":" ","investmentDiscretion":"SOLE","otherManager":" ","sole":"3,202,198","shared":"0","none":"0"},{"name":"UPWORK INC","class":"COM","cusip":"91688F104","value":"125,404","shares":"2,151,378","shPrn":"SH","putCall":" ","investmentDiscretion":"SOLE","otherManager":" ","sole":"2,151,378","shared":"0","none":"0"},{"name":"WIX COM LTD","class":"SHS","cusip":"M98068105","value":"183,113","shares":"630,815","shPrn":"SH","putCall":" ","investmentDiscretion":"SOLE","otherManager":" ","sole":"630,815","shared":"0","none":"0"}]